{
  "project_info": {
    "project_number": "659255109078",
    "project_id": "my-car-app-52e4f",
    "storage_bucket": "my-car-app-52e4f.appspot.com"
  },
  "client": [
    {
      "client_info": {
        "mobilesdk_app_id": "1:659255109078:android:6bbde50ed2fd6349397077",
        "android_client_info": {
          "package_name": "com.example.my_car_app_firebase"
        }
      },
      "oauth_client": [
        {
          "client_id": "659255109078-l667rhcei2jpoeia32mo3mci81hs40ku.apps.googleusercontent.com",
          "client_type": 3
        }
      ],
      "api_key": [
        {
          "current_key": "AIzaSyD4PB5r-aRotUeWRw-zBUyvGcrhRkuuDKc"
        }
      ],
      "services": {
        "appinvite_service": {
          "other_platform_oauth_client": [
            {
              "client_id": "659255109078-l667rhcei2jpoeia32mo3mci81hs40ku.apps.googleusercontent.com",
              "client_type": 3
            }
          ]
        }
      }
    }
  ],
  "configuration_version": "1"
}